wdpipe/__init__.py
wdpipe/astrometry/add_astrometry.py
wdpipe/inspection/__init__.py
wdpipe/inspection/filtering.py
wdpipe/inspection/inspect.py
wdpipe/photometry/__init__.py
wdpipe/photometry/aperture_phot.py
wdpipe/photometry/differential_phot.py
wdpipe/pre_processing/__init__.py
wdpipe/pre_processing/alignment.py
wdpipe/pre_processing/ccdred.py
wdpipe/pre_processing/combination.py
wdpipe/pre_processing/file_organization.py
wdpipe/pre_processing/nightlog.py
wdpipe/pre_processing/processes.py
wdpipe/utils/__init__.py
wdpipe/utils/context_managers.py
wildduckpipe-0.1.0.dist-info/licenses/LICENSE
wildduckpipe-0.1.0.dist-info/METADATA
wildduckpipe-0.1.0.dist-info/WHEEL
wildduckpipe-0.1.0.dist-info/top_level.txt
wildduckpipe-0.1.0.dist-info/RECORD
