Metadata-Version: 2.4
Name: wildduckpipe
Version: 0.1.0
Summary: Add your description here
Requires-Python: >=3.12
License-File: LICENSE
Requires-Dist: astroalign>=2.6.2
Requires-Dist: astropy>=7.1.0
Requires-Dist: ccdproc>=2.5.1
Requires-Dist: marimo>=0.17.0
Requires-Dist: matplotlib>=3.10.7
Requires-Dist: pandas>=2.3.3
Requires-Dist: photutils>=2.3.0
Dynamic: license-file
